hocke.py
hockepy/__init__.py
hockepy/commands/__init__.py
hockepy/commands/base_command.py
hockepy/commands/schedule.py
hockepy/commands/today.py
hockepy/config.py
hockepy/game.py
hockepy/log.py
hockepy/nhl.py
hockepy/utils.py
hockepy-0.2.dist-info/METADATA
hockepy-0.2.dist-info/WHEEL
hockepy-0.2.dist-info/entry_points.txt
hockepy-0.2.dist-info/RECORD
