Metadata-Version: 2.1
Name: hockepy
Version: 0.2
Summary: CLI utility and (a subset of) NHL API for hockey nerds
Home-page: https://github.com/geckon/hockepy
License: GPL-3.0-only
Author: Tomáš Heger
Requires-Python: >=3.7,<4.0
Classifier: License :: OSI Approved :: GNU General Public License v3 (GPLv3)
Classifier: Programming Language :: Python :: 3
Classifier: Programming Language :: Python :: 3.7
Classifier: Programming Language :: Python :: 3.8
Classifier: Programming Language :: Python :: 3.9
Classifier: Programming Language :: Python :: 3.10
Classifier: Programming Language :: Python :: 3.11
Requires-Dist: requests (>=2.24.0,<3.0.0)
Requires-Dist: toml (>=0.10.1,<0.11.0)
